autolog.py
autolog-0.2.dist-info/METADATA
autolog-0.2.dist-info/RECORD
autolog-0.2.dist-info/WHEEL
autolog-0.2.dist-info/top_level.txt
