Metadata-Version: 2.1
Name: autolog
Version: 0.2
Summary: quick and easy logging setup
Home-page: http://noble.gs.washington.edu/~mmh1/software/autolog/
Author: Michael Hoffman
Author-email: mmh1@uw.edu
License: GNU GPL v2
Download-URL: http://noble.gs.washington.edu/~mmh1/software/autolog//autolog-0.2.tar.gz
Platform: UNKNOWN
Classifier: License :: OSI Approved :: GNU General Public License (GPL)
Classifier: Natural Language :: English
Classifier: Programming Language :: Python
Requires-Dist: path.py
